HISTORY.rst
MANIFEST.in
NOTICE.rst
README.md
setup.py
bit9_api/__init__.py
bit9_api/api.py
bit9_api.egg-info/PKG-INFO
bit9_api.egg-info/SOURCES.txt
bit9_api.egg-info/dependency_links.txt
bit9_api.egg-info/requires.txt
bit9_api.egg-info/top_level.txt
doc/LICENSE
doc/README.rst