Metadata-Version: 1.0
Name: bit9-api
Version: 1.0.8
Summary: Bit9 API for their Cyber Forensics Service
Home-page: https://github.com/blacktop/bit9-api
Author: blacktop
Author-email: dev@blacktop.io
License: GPLv3
Platform: UNKNOWN
